{
  "nombre": { "es": "Bases de datos", "en": "Databases" },
  "orden": 2,
  "tecnologias": [
    { "id": "postgresql", "nombre": "PostgreSQL", "icono": "simple-icons:postgresql" },
    { "id": "sql-server", "nombre": "SQL Server", "icono": "simple-icons:microsoftsqlserver" },
    { "id": "mysql", "nombre": "MySQL", "icono": "simple-icons:mysql" },
    { "id": "sqlite", "nombre": "SQLite", "icono": "simple-icons:sqlite" },
    { "id": "supabase", "nombre": "Supabase", "icono": "simple-icons:supabase" }
  ]
}
